{
  "generated_at": "2026-04-20T08:27:36.941552+00:00",
  "feed_count": 1175,
  "version": 1776673656,
  "traditions": {
    "evangelical": 870,
    "baptist": 87,
    "catholic": 85,
    "reformed": 56,
    "charismatic": 27,
    "lutheran": 20,
    "methodist": 14,
    "episcopal": 10,
    "orthodox": 6
  },
  "sources": {
    "itunes-search": 664,
    "itunes-chart": 363,
    "podcast-index": 148
  },
  "popularity": {
    "feeds_with_signal": 469,
    "feeds_without_signal": 706,
    "top20": [
      {
        "speaker": "Ascension",
        "popularity": 1000
      },
      {
        "speaker": "Lakepointe Church",
        "popularity": 995
      },
      {
        "speaker": "Tara-Leigh Cobble",
        "popularity": 990
      },
      {
        "speaker": "Hank Smith & John Bytheway",
        "popularity": 985
      },
      {
        "speaker": "Tim Keller",
        "popularity": 975
      },
      {
        "speaker": "Blaze Podcast Network",
        "popularity": 970
      },
      {
        "speaker": "BibleProject Podcast",
        "popularity": 960
      },
      {
        "speaker": "The Robertson Family",
        "popularity": 955
      },
      {
        "speaker": "2819 Church",
        "popularity": 950
      },
      {
        "speaker": "Messenger International, John Bevere",
        "popularity": 940
      },
      {
        "speaker": "Matt Fradd",
        "popularity": 930
      },
      {
        "speaker": "BEMA Discipleship",
        "popularity": 915
      },
      {
        "speaker": "Ryan Miller",
        "popularity": 910
      },
      {
        "speaker": "Bryce Crawford",
        "popularity": 905
      },
      {
        "speaker": "iHeartPodcasts",
        "popularity": 900
      },
      {
        "speaker": "Ally Yost",
        "popularity": 895
      },
      {
        "speaker": "PROCLAIM x BIBLEin365",
        "popularity": 885
      },
      {
        "speaker": "Tara Brach",
        "popularity": 880
      },
      {
        "speaker": "Keeping Families Connected",
        "popularity": 875
      },
      {
        "speaker": "The Perrys",
        "popularity": 870
      }
    ]
  },
  "schema_version": 2
}
